.VERSION
AUTHORS.rst
CONTRIBUTING.rst
HISTORY.rst
LICENSE
MANIFEST.in
Pipfile
Pipfile.lock
README.rst
USAGE.rst
dev-requirements.txt
requirements.txt
setup.cfg
setup.py
_CI/__init__.py
_CI/configuration/__init__.py
_CI/configuration/configuration.py
_CI/library/__init__.py
_CI/library/library.py
_CI/scripts/__init__.py
_CI/scripts/bootstrap.py
_CI/scripts/build.py
_CI/scripts/document.py
_CI/scripts/graph.py
_CI/scripts/lint.py
_CI/scripts/tag.py
_CI/scripts/test.py
_CI/scripts/upload.py
docs/Makefile
docs/authors.rst
docs/conf.py
docs/contributing.rst
docs/history.rst
docs/index.rst
docs/installation.rst
docs/readme.rst
docs/usage.rst
winrmmanager/.VERSION
winrmmanager/__init__.py
winrmmanager/_version.py
winrmmanager/winrmmanager.py
winrmmanager/winrmmanagerexceptions.py
winrmmanager.egg-info/PKG-INFO
winrmmanager.egg-info/SOURCES.txt
winrmmanager.egg-info/dependency_links.txt
winrmmanager.egg-info/not-zip-safe
winrmmanager.egg-info/requires.txt
winrmmanager.egg-info/top_level.txt