Metadata-Version: 1.1
Name: winrmmanager
Version: 1.1.0
Summary: A project to create winrm sessions via python utilizing the pywinrm library
Home-page: https://github.com/schubergphilis/winrmmanager.git
Author: Gareth Hawker
Author-email: ghawker@schubergphilis.com
License: MIT
Keywords: winrmmanager winrm pywinrm
Platform: UNKNOWN
Classifier: Development Status :: 4 - Beta
Classifier: Intended Audience :: Developers
Classifier: License :: OSI Approved :: MIT License
Classifier: Natural Language :: English
Classifier: Programming Language :: Python :: 3.7
